bitbucket_jekyll_hook-0.1.post1.dist-info/metadata.json
bitbucket_jekyll_hook-0.1.post1.dist-info/METADATA
bitbucket_jekyll_hook-0.1.post1.dist-info/RECORD
bitbucket_jekyll_hook-0.1.post1.dist-info/top_level.txt
bitbucket_jekyll_hook-0.1.post1.dist-info/DESCRIPTION.rst
bitbucket_jekyll_hook-0.1.post1.dist-info/WHEEL
BB_jekyll_hook/__init__.py
BB_jekyll_hook/jekyll_hook.py
