Metadata-Version: 2.0
Name: bitbucket-jekyll-hook
Version: 0.1.post1
Summary: BitBucket webhook to trigger a static site build through Jekyll
Home-page: https://github.com/mattboyer/bitbucket_jekyll_hook
Author: Matt Boyer
Author-email: mboyer@sdf.org
License: BSD
Keywords: git webhook bitbucket jekyll publish
Platform: UNKNOWN
Classifier: Development Status :: 2 - Pre-Alpha
Classifier: Environment :: No Input/Output (Daemon)
Classifier: Framework :: Flask
Classifier: Intended Audience :: System Administrators
Classifier: License :: OSI Approved :: BSD License
Classifier: Operating System :: POSIX
Classifier: Programming Language :: Python :: 3 :: Only
Classifier: Topic :: Internet :: WWW/HTTP :: WSGI :: Application
Classifier: Topic :: Internet :: WWW/HTTP :: Site Management
Requires-Dist: flask
